atom3d/__init__.py
atom3d/data/__init__.py
atom3d/data/example.py
atom3d/datasets/__init__.py
atom3d/datasets/__main__.py
atom3d/datasets/datasets.py
atom3d/filters/__init__.py
atom3d/filters/filters.py
atom3d/filters/pdb.py
atom3d/filters/scop.py
atom3d/filters/sequence.py
atom3d/models/__init__.py
atom3d/models/cnn.py
atom3d/models/enn.py
atom3d/models/gnn.py
atom3d/models/mlp.py
atom3d/protein/__init__.py
atom3d/protein/scop.py
atom3d/protein/sequence.py
atom3d/splits/__init__.py
atom3d/splits/sequence.py
atom3d/splits/splits.py
atom3d/util/__init__.py
atom3d/util/ensemble.py
atom3d/util/file.py
atom3d/util/formats.py
atom3d/util/graph.py
atom3d/util/log.py
atom3d/util/metrics.py
atom3d/util/results.py
atom3d/util/rosetta.py
atom3d/util/transforms.py
atom3d/util/vectors.py
atom3d/util/voxelize.py
atom3d-0.2.6.dist-info/LICENSE
atom3d-0.2.6.dist-info/METADATA
atom3d-0.2.6.dist-info/WHEEL
atom3d-0.2.6.dist-info/top_level.txt
atom3d-0.2.6.dist-info/RECORD
