Metadata-Version: 2.1
Name: atom3d
Version: 0.2.6
Summary: ATOM3D: Tasks On Molecules in 3 Dimensions
Home-page: https://www.atom3d.ai
Author: ATOM3D developers
License: MIT
Platform: UNKNOWN
License-File: LICENSE
Requires-Dist: argparse
Requires-Dist: biopython
Requires-Dist: click
Requires-Dist: easy-parallel
Requires-Dist: freesasa
Requires-Dist: h5py
Requires-Dist: lmdb
Requires-Dist: msgpack
Requires-Dist: numpy
Requires-Dist: pandas
Requires-Dist: pyrr
Requires-Dist: python-dotenv (>=0.5.1)
Requires-Dist: scipy
Requires-Dist: scikit-learn
Requires-Dist: tables
Requires-Dist: torch
Requires-Dist: tqdm
